verbix_sdk/__about__.py
verbix_sdk/__init__.py
verbix_sdk/constants.py
verbix_sdk/v1.py
verbix_sdk/v2.py
verbix_sdk-0.0.2.dist-info/METADATA
verbix_sdk-0.0.2.dist-info/WHEEL
verbix_sdk-0.0.2.dist-info/licenses/LICENSE.txt
verbix_sdk-0.0.2.dist-info/RECORD
