Metadata-Version: 2.1
Name: verbix-sdk
Version: 0.0.2
Summary: Verbix unofficial SDK
Project-URL: Documentation, https://github.com/ZanSara/verbix-sdk#readme
Project-URL: Issues, https://github.com/ZanSara/verbix-sdk/issues
Project-URL: Source, https://github.com/ZanSara/verbix-sdk
Author-email: ZanSara <verbixsdk@zanzohegyi.com>
License-Expression: MIT
License-File: LICENSE.txt
Classifier: Development Status :: 4 - Beta
Classifier: Programming Language :: Python
Classifier: Programming Language :: Python :: 3.7
Classifier: Programming Language :: Python :: 3.8
Classifier: Programming Language :: Python :: 3.9
Classifier: Programming Language :: Python :: 3.10
Classifier: Programming Language :: Python :: 3.11
Classifier: Programming Language :: Python :: Implementation :: CPython
Classifier: Programming Language :: Python :: Implementation :: PyPy
Requires-Python: >=3.7
Requires-Dist: beautifulsoup4
Requires-Dist: requests
